{
  "manifestVersion": "3.2",
  "admin": {
    "address": "0x481CCcc5b24b83b9D4a59E1B3c6Dc1924D0bEFCF",
    "txHash": "0x5825a0af04755fc60ed634e38f10b855ac48f3b1895688c536d4a04a7c3a47a8"
  },
  "proxies": [
    {
      "address": "0x002A04822dB995841b04F0cd7bc689B38Ad6dEC7",
      "txHash": "0x39b1217a584a866bc15648808b14794c771c2035782ae7d49e6414738e9ffec4",
      "kind": "transparent"
    },
    {
      "address": "0x75A2D1c4fd6b56E31180e6244c72Cb9a5fc8F935",
      "txHash": "0xc7bff322db0d843c103c6c0ed125d061f5ac37c528f94c7ca70db5480d3ff476",
      "kind": "transparent"
    },
    {
      "address": "0x3aE5A2f4a84B61Ebbe7B56754175bE305fa05d10",
      "txHash": "0x54e028dd5ac56b11008702df1502c678f421b173f90831457a20e223bfd66453",
      "kind": "transparent"
    },
    {
      "address": "0xD0A04300B06b0b972D26aB328BbfFbD80Ee2B8a2",
      "txHash": "0x6f5ae528d15069369909b756c60e8868ec9ca6c07a7ea4a91efb9b76747c43ab",
      "kind": "transparent"
    },
    {
      "address": "0x2EdbCdDA85CC393b1104BE2Db62D7C0028dE88Fa",
      "txHash": "0x7f5418aa073dc5fadaba0ed962bfd216f968b61ebdd3488b7195e3924108177d",
      "kind": "transparent"
    },
    {
      "address": "0xA79BFAF502D5025B011cc7E8471b03193fC88F09",
      "txHash": "0xcdbe36441ec0d337fa15d58d5566f21933879da29c9c5e8fbb762727e859b1cd",
      "kind": "transparent"
    }
  ],
  "impls": {
    "d6ed452eda51e14381aef0b5e94488f5066c42924acd3acb1059c5491b121066": {
      "address": "0x28C0D71Ea944D0E15e2148545bc3f943F8B48877",
      "txHash": "0x5b47de4adefd7088b7de4b7e744219c44505094c79930bee21c4997a1c5960fd",
      "layout": {
        "solcVersion": "0.8.16",
        "storage": [
          {
            "label": "_shareholderRegistry",
            "offset": 0,
            "slot": "0",
            "type": "t_contract(IShareholderRegistry)10361",
            "contract": "VotingBase",
            "src": "contracts/Voting/VotingBase.sol:21"
          },
          {
            "label": "_token",
            "offset": 0,
            "slot": "1",
            "type": "t_contract(IERC20Upgradeable)1267",
            "contract": "VotingBase",
            "src": "contracts/Voting/VotingBase.sol:22"
          },
          {
            "label": "_contributorRole",
            "offset": 0,
            "slot": "2",
            "type": "t_bytes32",
            "contract": "VotingBase",
            "src": "contracts/Voting/VotingBase.sol:24"
          },
          {
            "label": "_delegates",
            "offset": 0,
            "slot": "3",
            "type": "t_mapping(t_address,t_address)",
            "contract": "VotingBase",
            "src": "contracts/Voting/VotingBase.sol:26"
          },
          {
            "label": "_votingPower",
            "offset": 0,
            "slot": "4",
            "type": "t_mapping(t_address,t_uint256)",
            "contract": "VotingBase",
            "src": "contracts/Voting/VotingBase.sol:27"
          },
          {
            "label": "_delegators",
            "offset": 0,
            "slot": "5",
            "type": "t_mapping(t_address,t_uint256)",
            "contract": "VotingBase",
            "src": "contracts/Voting/VotingBase.sol:28"
          },
          {
            "label": "_totalVotingPower",
            "offset": 0,
            "slot": "6",
            "type": "t_uint256",
            "contract": "VotingBase",
            "src": "contracts/Voting/VotingBase.sol:30"
          },
          {
            "label": "_currentSnapshotId",
            "offset": 0,
            "slot": "7",
            "type": "t_uint256",
            "contract": "Snapshottable",
            "src": "contracts/extensions/Snapshottable.sol:11"
          },
          {
            "label": "_delegationSnapshots",
            "offset": 0,
            "slot": "8",
            "type": "t_mapping(t_address,t_struct(SnapshotsDelegates)12186_storage)",
            "contract": "VotingSnapshot",
            "src": "contracts/Voting/VotingSnapshot.sol:21"
          },
          {
            "label": "_votingPowerSnapshots",
            "offset": 0,
            "slot": "9",
            "type": "t_mapping(t_address,t_struct(SnapshotsValues)12193_storage)",
            "contract": "VotingSnapshot",
            "src": "contracts/Voting/VotingSnapshot.sol:22"
          },
          {
            "label": "_totalVotingPowerSnapshots",
            "offset": 0,
            "slot": "10",
            "type": "t_struct(SnapshotsValues)12193_storage",
            "contract": "VotingSnapshot",
            "src": "contracts/Voting/VotingSnapshot.sol:23"
          },
          {
            "label": "_initialized",
            "offset": 0,
            "slot": "12",
            "type": "t_uint8",
            "contract": "Initializable",
            "src": "@openzeppelin/contracts-upgradeable/proxy/utils/Initializable.sol:62",
            "retypedFrom": "bool"
          },
          {
            "label": "_initializing",
            "offset": 1,
            "slot": "12",
            "type": "t_bool",
            "contract": "Initializable",
            "src": "@openzeppelin/contracts-upgradeable/proxy/utils/Initializable.sol:67"
          },
          {
            "label": "__gap",
            "offset": 0,
            "slot": "13",
            "type": "t_array(t_uint256)50_storage",
            "contract": "ContextUpgradeable",
            "src": "@openzeppelin/contracts-upgradeable/utils/ContextUpgradeable.sol:36"
          },
          {
            "label": "_roles",
            "offset": 0,
            "slot": "63",
            "type": "t_contract(DAORoles)12510",
            "contract": "HasRole",
            "src": "contracts/extensions/HasRole.sol:11"
          }
        ],
        "types": {
          "t_address": {
            "label": "address",
            "numberOfBytes": "20"
          },
          "t_array(t_address)dyn_storage": {
            "label": "address[]",
            "numberOfBytes": "32"
          },
          "t_array(t_uint256)50_storage": {
            "label": "uint256[50]",
            "numberOfBytes": "1600"
          },
          "t_array(t_uint256)dyn_storage": {
            "label": "uint256[]",
            "numberOfBytes": "32"
          },
          "t_bool": {
            "label": "bool",
            "numberOfBytes": "1"
          },
          "t_bytes32": {
            "label": "bytes32",
            "numberOfBytes": "32"
          },
          "t_contract(DAORoles)12510": {
            "label": "contract DAORoles",
            "numberOfBytes": "20"
          },
          "t_contract(IERC20Upgradeable)1267": {
            "label": "contract IERC20Upgradeable",
            "numberOfBytes": "20"
          },
          "t_contract(IShareholderRegistry)10361": {
            "label": "contract IShareholderRegistry",
            "numberOfBytes": "20"
          },
          "t_mapping(t_address,t_address)": {
            "label": "mapping(address => address)",
            "numberOfBytes": "32"
          },
          "t_mapping(t_address,t_struct(SnapshotsDelegates)12186_storage)": {
            "label": "mapping(address => struct VotingSnapshot.SnapshotsDelegates)",
            "numberOfBytes": "32"
          },
          "t_mapping(t_address,t_struct(SnapshotsValues)12193_storage)": {
            "label": "mapping(address => struct VotingSnapshot.SnapshotsValues)",
            "numberOfBytes": "32"
          },
          "t_mapping(t_address,t_uint256)": {
            "label": "mapping(address => uint256)",
            "numberOfBytes": "32"
          },
          "t_struct(SnapshotsDelegates)12186_storage": {
            "label": "struct VotingSnapshot.SnapshotsDelegates",
            "members": [
              {
                "label": "ids",
                "type": "t_array(t_uint256)dyn_storage",
                "offset": 0,
                "slot": "0"
              },
              {
                "label": "delegates",
                "type": "t_array(t_address)dyn_storage",
                "offset": 0,
                "slot": "1"
              }
            ],
            "numberOfBytes": "64"
          },
          "t_struct(SnapshotsValues)12193_storage": {
            "label": "struct VotingSnapshot.SnapshotsValues",
            "members": [
              {
                "label": "ids",
                "type": "t_array(t_uint256)dyn_storage",
                "offset": 0,
                "slot": "0"
              },
              {
                "label": "values",
                "type": "t_array(t_uint256)dyn_storage",
                "offset": 0,
                "slot": "1"
              }
            ],
            "numberOfBytes": "64"
          },
          "t_uint256": {
            "label": "uint256",
            "numberOfBytes": "32"
          },
          "t_uint8": {
            "label": "uint8",
            "numberOfBytes": "1"
          }
        }
      }
    },
    "b3a29b0623c1c9376ea5cbbb675ba9d166e6da725a4ccc39f49239471ac22e77": {
      "address": "0x314Bbb4801BA6B8b0Bf9Cb96e71bd1e592869d14",
      "txHash": "0x23711eb63e2bc175832ad95028639bd96558ba506c3b6d87b2efcf3bb35c8aad",
      "layout": {
        "solcVersion": "0.8.16",
        "storage": [
          {
            "label": "_initialized",
            "offset": 0,
            "slot": "0",
            "type": "t_uint8",
            "contract": "Initializable",
            "src": "@openzeppelin/contracts-upgradeable/proxy/utils/Initializable.sol:62",
            "retypedFrom": "bool"
          },
          {
            "label": "_initializing",
            "offset": 1,
            "slot": "0",
            "type": "t_bool",
            "contract": "Initializable",
            "src": "@openzeppelin/contracts-upgradeable/proxy/utils/Initializable.sol:67"
          },
          {
            "label": "__gap",
            "offset": 0,
            "slot": "1",
            "type": "t_array(t_uint256)50_storage",
            "contract": "ContextUpgradeable",
            "src": "@openzeppelin/contracts-upgradeable/utils/ContextUpgradeable.sol:36"
          },
          {
            "label": "_roles",
            "offset": 0,
            "slot": "51",
            "type": "t_contract(DAORoles)12510",
            "contract": "HasRole",
            "src": "contracts/extensions/HasRole.sol:11"
          },
          {
            "label": "_balances",
            "offset": 0,
            "slot": "52",
            "type": "t_mapping(t_address,t_uint256)",
            "contract": "ERC20Upgradeable",
            "src": "@openzeppelin/contracts-upgradeable/token/ERC20/ERC20Upgradeable.sol:37"
          },
          {
            "label": "_allowances",
            "offset": 0,
            "slot": "53",
            "type": "t_mapping(t_address,t_mapping(t_address,t_uint256))",
            "contract": "ERC20Upgradeable",
            "src": "@openzeppelin/contracts-upgradeable/token/ERC20/ERC20Upgradeable.sol:39"
          },
          {
            "label": "_totalSupply",
            "offset": 0,
            "slot": "54",
            "type": "t_uint256",
            "contract": "ERC20Upgradeable",
            "src": "@openzeppelin/contracts-upgradeable/token/ERC20/ERC20Upgradeable.sol:41"
          },
          {
            "label": "_name",
            "offset": 0,
            "slot": "55",
            "type": "t_string_storage",
            "contract": "ERC20Upgradeable",
            "src": "@openzeppelin/contracts-upgradeable/token/ERC20/ERC20Upgradeable.sol:43"
          },
          {
            "label": "_symbol",
            "offset": 0,
            "slot": "56",
            "type": "t_string_storage",
            "contract": "ERC20Upgradeable",
            "src": "@openzeppelin/contracts-upgradeable/token/ERC20/ERC20Upgradeable.sol:44"
          },
          {
            "label": "__gap",
            "offset": 0,
            "slot": "57",
            "type": "t_array(t_uint256)45_storage",
            "contract": "ERC20Upgradeable",
            "src": "@openzeppelin/contracts-upgradeable/token/ERC20/ERC20Upgradeable.sol:400"
          },
          {
            "label": "_voting",
            "offset": 0,
            "slot": "102",
            "type": "t_contract(IVoting)11408",
            "contract": "GovernanceTokenBase",
            "src": "contracts/GovernanceToken/GovernanceTokenBase.sol:14"
          },
          {
            "label": "_redemptionController",
            "offset": 0,
            "slot": "103",
            "type": "t_contract(IRedemptionController)7911",
            "contract": "GovernanceTokenBase",
            "src": "contracts/GovernanceToken/GovernanceTokenBase.sol:15"
          },
          {
            "label": "tokenExternal",
            "offset": 0,
            "slot": "104",
            "type": "t_contract(INeokingdomToken)7824",
            "contract": "GovernanceTokenBase",
            "src": "contracts/GovernanceToken/GovernanceTokenBase.sol:16"
          },
          {
            "label": "_vestingBalance",
            "offset": 0,
            "slot": "105",
            "type": "t_mapping(t_address,t_uint256)",
            "contract": "GovernanceTokenBase",
            "src": "contracts/GovernanceToken/GovernanceTokenBase.sol:27"
          },
          {
            "label": "_currentSnapshotId",
            "offset": 0,
            "slot": "106",
            "type": "t_uint256",
            "contract": "Snapshottable",
            "src": "contracts/extensions/Snapshottable.sol:11"
          },
          {
            "label": "_accountBalanceSnapshots",
            "offset": 0,
            "slot": "107",
            "type": "t_mapping(t_address,t_struct(Snapshots)6365_storage)",
            "contract": "GovernanceTokenSnapshot",
            "src": "contracts/GovernanceToken/GovernanceTokenSnapshot.sol:20"
          },
          {
            "label": "_totalSupplySnapshots",
            "offset": 0,
            "slot": "108",
            "type": "t_struct(Snapshots)6365_storage",
            "contract": "GovernanceTokenSnapshot",
            "src": "contracts/GovernanceToken/GovernanceTokenSnapshot.sol:21"
          },
          {
            "label": "_shareholderRegistry",
            "offset": 0,
            "slot": "110",
            "type": "t_contract(IShareholderRegistry)10361",
            "contract": "GovernanceToken",
            "src": "contracts/GovernanceToken/GovernanceToken.sol:20"
          },
          {
            "label": "depositedTokens",
            "offset": 0,
            "slot": "111",
            "type": "t_mapping(t_address,t_array(t_struct(DepositedTokens)5524_storage)dyn_storage)",
            "contract": "GovernanceToken",
            "src": "contracts/GovernanceToken/GovernanceToken.sol:36"
          },
          {
            "label": "settlementPeriod",
            "offset": 0,
            "slot": "112",
            "type": "t_uint256",
            "contract": "GovernanceToken",
            "src": "contracts/GovernanceToken/GovernanceToken.sol:38"
          }
        ],
        "types": {
          "t_address": {
            "label": "address",
            "numberOfBytes": "20"
          },
          "t_array(t_struct(DepositedTokens)5524_storage)dyn_storage": {
            "label": "struct GovernanceToken.DepositedTokens[]",
            "numberOfBytes": "32"
          },
          "t_array(t_uint256)45_storage": {
            "label": "uint256[45]",
            "numberOfBytes": "1440"
          },
          "t_array(t_uint256)50_storage": {
            "label": "uint256[50]",
            "numberOfBytes": "1600"
          },
          "t_array(t_uint256)dyn_storage": {
            "label": "uint256[]",
            "numberOfBytes": "32"
          },
          "t_bool": {
            "label": "bool",
            "numberOfBytes": "1"
          },
          "t_contract(DAORoles)12510": {
            "label": "contract DAORoles",
            "numberOfBytes": "20"
          },
          "t_contract(INeokingdomToken)7824": {
            "label": "contract INeokingdomToken",
            "numberOfBytes": "20"
          },
          "t_contract(IRedemptionController)7911": {
            "label": "contract IRedemptionController",
            "numberOfBytes": "20"
          },
          "t_contract(IShareholderRegistry)10361": {
            "label": "contract IShareholderRegistry",
            "numberOfBytes": "20"
          },
          "t_contract(IVoting)11408": {
            "label": "contract IVoting",
            "numberOfBytes": "20"
          },
          "t_mapping(t_address,t_array(t_struct(DepositedTokens)5524_storage)dyn_storage)": {
            "label": "mapping(address => struct GovernanceToken.DepositedTokens[])",
            "numberOfBytes": "32"
          },
          "t_mapping(t_address,t_mapping(t_address,t_uint256))": {
            "label": "mapping(address => mapping(address => uint256))",
            "numberOfBytes": "32"
          },
          "t_mapping(t_address,t_struct(Snapshots)6365_storage)": {
            "label": "mapping(address => struct GovernanceTokenSnapshot.Snapshots)",
            "numberOfBytes": "32"
          },
          "t_mapping(t_address,t_uint256)": {
            "label": "mapping(address => uint256)",
            "numberOfBytes": "32"
          },
          "t_string_storage": {
            "label": "string",
            "numberOfBytes": "32"
          },
          "t_struct(DepositedTokens)5524_storage": {
            "label": "struct GovernanceToken.DepositedTokens",
            "members": [
              {
                "label": "amount",
                "type": "t_uint256",
                "offset": 0,
                "slot": "0"
              },
              {
                "label": "settlementTimestamp",
                "type": "t_uint256",
                "offset": 0,
                "slot": "1"
              }
            ],
            "numberOfBytes": "64"
          },
          "t_struct(Snapshots)6365_storage": {
            "label": "struct GovernanceTokenSnapshot.Snapshots",
            "members": [
              {
                "label": "ids",
                "type": "t_array(t_uint256)dyn_storage",
                "offset": 0,
                "slot": "0"
              },
              {
                "label": "values",
                "type": "t_array(t_uint256)dyn_storage",
                "offset": 0,
                "slot": "1"
              }
            ],
            "numberOfBytes": "64"
          },
          "t_uint256": {
            "label": "uint256",
            "numberOfBytes": "32"
          },
          "t_uint8": {
            "label": "uint8",
            "numberOfBytes": "1"
          }
        }
      }
    },
    "8cde9a7dc080407d495d77085a5bdefff4593ff8a008725ccf308f418fa6998b": {
      "address": "0x258c7991b0664e13B62AA530237f056CbC187F29",
      "txHash": "0x1c600524e351e59e93dcb67ebfffb85f51eb9e19129471de84c2b61235d7f7e5",
      "layout": {
        "solcVersion": "0.8.16",
        "storage": [
          {
            "label": "_initialized",
            "offset": 0,
            "slot": "0",
            "type": "t_uint8",
            "contract": "Initializable",
            "src": "@openzeppelin/contracts-upgradeable/proxy/utils/Initializable.sol:62",
            "retypedFrom": "bool"
          },
          {
            "label": "_initializing",
            "offset": 1,
            "slot": "0",
            "type": "t_bool",
            "contract": "Initializable",
            "src": "@openzeppelin/contracts-upgradeable/proxy/utils/Initializable.sol:67"
          },
          {
            "label": "__gap",
            "offset": 0,
            "slot": "1",
            "type": "t_array(t_uint256)50_storage",
            "contract": "ContextUpgradeable",
            "src": "@openzeppelin/contracts-upgradeable/utils/ContextUpgradeable.sol:36"
          },
          {
            "label": "_roles",
            "offset": 0,
            "slot": "51",
            "type": "t_contract(DAORoles)12510",
            "contract": "HasRole",
            "src": "contracts/extensions/HasRole.sol:11"
          },
          {
            "label": "redemptionStart",
            "offset": 0,
            "slot": "52",
            "type": "t_uint256",
            "contract": "RedemptionControllerBase",
            "src": "contracts/RedemptionController/RedemptionControllerBase.sol:21"
          },
          {
            "label": "redemptionWindow",
            "offset": 0,
            "slot": "53",
            "type": "t_uint256",
            "contract": "RedemptionControllerBase",
            "src": "contracts/RedemptionController/RedemptionControllerBase.sol:22"
          },
          {
            "label": "maxDaysInThePast",
            "offset": 0,
            "slot": "54",
            "type": "t_uint256",
            "contract": "RedemptionControllerBase",
            "src": "contracts/RedemptionController/RedemptionControllerBase.sol:24"
          },
          {
            "label": "activityWindow",
            "offset": 0,
            "slot": "55",
            "type": "t_uint256",
            "contract": "RedemptionControllerBase",
            "src": "contracts/RedemptionController/RedemptionControllerBase.sol:25"
          },
          {
            "label": "_redeemables",
            "offset": 0,
            "slot": "56",
            "type": "t_mapping(t_address,t_array(t_struct(Redeemable)8036_storage)dyn_storage)",
            "contract": "RedemptionControllerBase",
            "src": "contracts/RedemptionController/RedemptionControllerBase.sol:27"
          },
          {
            "label": "_redeemablesFirst",
            "offset": 0,
            "slot": "57",
            "type": "t_mapping(t_address,t_uint256)",
            "contract": "RedemptionControllerBase",
            "src": "contracts/RedemptionController/RedemptionControllerBase.sol:28"
          },
          {
            "label": "_mintBudgets",
            "offset": 0,
            "slot": "58",
            "type": "t_mapping(t_address,t_array(t_struct(MintBudget)8041_storage)dyn_storage)",
            "contract": "RedemptionControllerBase",
            "src": "contracts/RedemptionController/RedemptionControllerBase.sol:30"
          },
          {
            "label": "_mintBudgetsStartIndex",
            "offset": 0,
            "slot": "59",
            "type": "t_mapping(t_address,t_uint256)",
            "contract": "RedemptionControllerBase",
            "src": "contracts/RedemptionController/RedemptionControllerBase.sol:31"
          }
        ],
        "types": {
          "t_address": {
            "label": "address",
            "numberOfBytes": "20"
          },
          "t_array(t_struct(MintBudget)8041_storage)dyn_storage": {
            "label": "struct RedemptionControllerBase.MintBudget[]",
            "numberOfBytes": "32"
          },
          "t_array(t_struct(Redeemable)8036_storage)dyn_storage": {
            "label": "struct RedemptionControllerBase.Redeemable[]",
            "numberOfBytes": "32"
          },
          "t_array(t_uint256)50_storage": {
            "label": "uint256[50]",
            "numberOfBytes": "1600"
          },
          "t_bool": {
            "label": "bool",
            "numberOfBytes": "1"
          },
          "t_contract(DAORoles)12510": {
            "label": "contract DAORoles",
            "numberOfBytes": "20"
          },
          "t_mapping(t_address,t_array(t_struct(MintBudget)8041_storage)dyn_storage)": {
            "label": "mapping(address => struct RedemptionControllerBase.MintBudget[])",
            "numberOfBytes": "32"
          },
          "t_mapping(t_address,t_array(t_struct(Redeemable)8036_storage)dyn_storage)": {
            "label": "mapping(address => struct RedemptionControllerBase.Redeemable[])",
            "numberOfBytes": "32"
          },
          "t_mapping(t_address,t_uint256)": {
            "label": "mapping(address => uint256)",
            "numberOfBytes": "32"
          },
          "t_struct(MintBudget)8041_storage": {
            "label": "struct RedemptionControllerBase.MintBudget",
            "members": [
              {
                "label": "timestamp",
                "type": "t_uint256",
                "offset": 0,
                "slot": "0"
              },
              {
                "label": "amount",
                "type": "t_uint256",
                "offset": 0,
                "slot": "1"
              }
            ],
            "numberOfBytes": "64"
          },
          "t_struct(Redeemable)8036_storage": {
            "label": "struct RedemptionControllerBase.Redeemable",
            "members": [
              {
                "label": "amount",
                "type": "t_uint256",
                "offset": 0,
                "slot": "0"
              },
              {
                "label": "mintTimestamp",
                "type": "t_uint256",
                "offset": 0,
                "slot": "1"
              },
              {
                "label": "start",
                "type": "t_uint256",
                "offset": 0,
                "slot": "2"
              },
              {
                "label": "end",
                "type": "t_uint256",
                "offset": 0,
                "slot": "3"
              }
            ],
            "numberOfBytes": "128"
          },
          "t_uint256": {
            "label": "uint256",
            "numberOfBytes": "32"
          },
          "t_uint8": {
            "label": "uint8",
            "numberOfBytes": "1"
          }
        }
      }
    },
    "9785844e8df3779bd6ed907944e66fc688c2419cffcde31dd5b7dd9e113b5dab": {
      "address": "0x1C658917B1e8A168Eb35E2D0943929167a75Ef83",
      "txHash": "0x2663b7ad899d25175f1604b1e21419076d91b75aa95764a2bf14d03ddc049991",
      "layout": {
        "solcVersion": "0.8.16",
        "storage": [
          {
            "label": "_initialized",
            "offset": 0,
            "slot": "0",
            "type": "t_uint8",
            "contract": "Initializable",
            "src": "@openzeppelin/contracts-upgradeable/proxy/utils/Initializable.sol:62",
            "retypedFrom": "bool"
          },
          {
            "label": "_initializing",
            "offset": 1,
            "slot": "0",
            "type": "t_bool",
            "contract": "Initializable",
            "src": "@openzeppelin/contracts-upgradeable/proxy/utils/Initializable.sol:67"
          },
          {
            "label": "__gap",
            "offset": 0,
            "slot": "1",
            "type": "t_array(t_uint256)50_storage",
            "contract": "ContextUpgradeable",
            "src": "@openzeppelin/contracts-upgradeable/utils/ContextUpgradeable.sol:36"
          },
          {
            "label": "_roles",
            "offset": 0,
            "slot": "51",
            "type": "t_contract(DAORoles)7690",
            "contract": "HasRole",
            "src": "contracts/extensions/HasRole.sol:11"
          },
          {
            "label": "tokenInternal",
            "offset": 0,
            "slot": "52",
            "type": "t_contract(IGovernanceToken)6275",
            "contract": "InternalMarketBase",
            "src": "contracts/InternalMarket/InternalMarketBase.sol:33"
          },
          {
            "label": "exchangeToken",
            "offset": 0,
            "slot": "53",
            "type": "t_contract(ERC20)3690",
            "contract": "InternalMarketBase",
            "src": "contracts/InternalMarket/InternalMarketBase.sol:36"
          },
          {
            "label": "redemptionController",
            "offset": 0,
            "slot": "54",
            "type": "t_contract(IRedemptionController)7480",
            "contract": "InternalMarketBase",
            "src": "contracts/InternalMarket/InternalMarketBase.sol:38"
          },
          {
            "label": "priceOracle",
            "offset": 0,
            "slot": "55",
            "type": "t_contract(IDIAOracleV2)6301",
            "contract": "InternalMarketBase",
            "src": "contracts/InternalMarket/InternalMarketBase.sol:39"
          },
          {
            "label": "_shareholderRegistry",
            "offset": 0,
            "slot": "56",
            "type": "t_contract(IShareholderRegistry)7577",
            "contract": "InternalMarketBase",
            "src": "contracts/InternalMarket/InternalMarketBase.sol:40"
          },
          {
            "label": "reserve",
            "offset": 0,
            "slot": "57",
            "type": "t_address",
            "contract": "InternalMarketBase",
            "src": "contracts/InternalMarket/InternalMarketBase.sol:42"
          },
          {
            "label": "offerDuration",
            "offset": 0,
            "slot": "58",
            "type": "t_uint256",
            "contract": "InternalMarketBase",
            "src": "contracts/InternalMarket/InternalMarketBase.sol:43"
          },
          {
            "label": "_offers",
            "offset": 0,
            "slot": "59",
            "type": "t_mapping(t_address,t_struct(Offers)6670_storage)",
            "contract": "InternalMarketBase",
            "src": "contracts/InternalMarket/InternalMarketBase.sol:45"
          },
          {
            "label": "_vaultContributors",
            "offset": 0,
            "slot": "60",
            "type": "t_mapping(t_address,t_uint256)",
            "contract": "InternalMarketBase",
            "src": "contracts/InternalMarket/InternalMarketBase.sol:47"
          },
          {
            "label": "_diaPriceOracle",
            "offset": 0,
            "slot": "61",
            "type": "t_contract(IDIAOracleV2)6301",
            "contract": "InternalMarket",
            "src": "contracts/InternalMarket/InternalMarket.sol:20"
          }
        ],
        "types": {
          "t_address": {
            "label": "address",
            "numberOfBytes": "20"
          },
          "t_array(t_uint256)50_storage": {
            "label": "uint256[50]",
            "numberOfBytes": "1600"
          },
          "t_bool": {
            "label": "bool",
            "numberOfBytes": "1"
          },
          "t_contract(DAORoles)7690": {
            "label": "contract DAORoles",
            "numberOfBytes": "20"
          },
          "t_contract(ERC20)3690": {
            "label": "contract ERC20",
            "numberOfBytes": "20"
          },
          "t_contract(IDIAOracleV2)6301": {
            "label": "contract IDIAOracleV2",
            "numberOfBytes": "20"
          },
          "t_contract(IGovernanceToken)6275": {
            "label": "contract IGovernanceToken",
            "numberOfBytes": "20"
          },
          "t_contract(IRedemptionController)7480": {
            "label": "contract IRedemptionController",
            "numberOfBytes": "20"
          },
          "t_contract(IShareholderRegistry)7577": {
            "label": "contract IShareholderRegistry",
            "numberOfBytes": "20"
          },
          "t_mapping(t_address,t_struct(Offers)6670_storage)": {
            "label": "mapping(address => struct InternalMarketBase.Offers)",
            "numberOfBytes": "32"
          },
          "t_mapping(t_address,t_uint256)": {
            "label": "mapping(address => uint256)",
            "numberOfBytes": "32"
          },
          "t_mapping(t_uint128,t_struct(Offer)6660_storage)": {
            "label": "mapping(uint128 => struct InternalMarketBase.Offer)",
            "numberOfBytes": "32"
          },
          "t_struct(Offer)6660_storage": {
            "label": "struct InternalMarketBase.Offer",
            "members": [
              {
                "label": "expiredAt",
                "type": "t_uint256",
                "offset": 0,
                "slot": "0"
              },
              {
                "label": "amount",
                "type": "t_uint256",
                "offset": 0,
                "slot": "1"
              }
            ],
            "numberOfBytes": "64"
          },
          "t_struct(Offers)6670_storage": {
            "label": "struct InternalMarketBase.Offers",
            "members": [
              {
                "label": "start",
                "type": "t_uint128",
                "offset": 0,
                "slot": "0"
              },
              {
                "label": "end",
                "type": "t_uint128",
                "offset": 16,
                "slot": "0"
              },
              {
                "label": "offer",
                "type": "t_mapping(t_uint128,t_struct(Offer)6660_storage)",
                "offset": 0,
                "slot": "1"
              }
            ],
            "numberOfBytes": "64"
          },
          "t_uint128": {
            "label": "uint128",
            "numberOfBytes": "16"
          },
          "t_uint256": {
            "label": "uint256",
            "numberOfBytes": "32"
          },
          "t_uint8": {
            "label": "uint8",
            "numberOfBytes": "1"
          }
        }
      }
    },
    "470f1646ac663c891ce27799fe38f09bf2337c0262107e89c62107f68f507412": {
      "address": "0xBbCbA7f8c66A34256BbDff4bd80dDE7E26eDB1f1",
      "txHash": "0x437d826969d07230d59b48dfbbfc9b0b46868123668e4827bc9c18e1f5f14fff",
      "layout": {
        "solcVersion": "0.8.16",
        "storage": [
          {
            "label": "_initialized",
            "offset": 0,
            "slot": "0",
            "type": "t_uint8",
            "contract": "Initializable",
            "src": "@openzeppelin/contracts-upgradeable/proxy/utils/Initializable.sol:62",
            "retypedFrom": "bool"
          },
          {
            "label": "_initializing",
            "offset": 1,
            "slot": "0",
            "type": "t_bool",
            "contract": "Initializable",
            "src": "@openzeppelin/contracts-upgradeable/proxy/utils/Initializable.sol:67"
          },
          {
            "label": "__gap",
            "offset": 0,
            "slot": "1",
            "type": "t_array(t_uint256)50_storage",
            "contract": "ContextUpgradeable",
            "src": "@openzeppelin/contracts-upgradeable/utils/ContextUpgradeable.sol:36"
          },
          {
            "label": "_balances",
            "offset": 0,
            "slot": "51",
            "type": "t_mapping(t_address,t_uint256)",
            "contract": "ERC20Upgradeable",
            "src": "@openzeppelin/contracts-upgradeable/token/ERC20/ERC20Upgradeable.sol:37"
          },
          {
            "label": "_allowances",
            "offset": 0,
            "slot": "52",
            "type": "t_mapping(t_address,t_mapping(t_address,t_uint256))",
            "contract": "ERC20Upgradeable",
            "src": "@openzeppelin/contracts-upgradeable/token/ERC20/ERC20Upgradeable.sol:39"
          },
          {
            "label": "_totalSupply",
            "offset": 0,
            "slot": "53",
            "type": "t_uint256",
            "contract": "ERC20Upgradeable",
            "src": "@openzeppelin/contracts-upgradeable/token/ERC20/ERC20Upgradeable.sol:41"
          },
          {
            "label": "_name",
            "offset": 0,
            "slot": "54",
            "type": "t_string_storage",
            "contract": "ERC20Upgradeable",
            "src": "@openzeppelin/contracts-upgradeable/token/ERC20/ERC20Upgradeable.sol:43"
          },
          {
            "label": "_symbol",
            "offset": 0,
            "slot": "55",
            "type": "t_string_storage",
            "contract": "ERC20Upgradeable",
            "src": "@openzeppelin/contracts-upgradeable/token/ERC20/ERC20Upgradeable.sol:44"
          },
          {
            "label": "__gap",
            "offset": 0,
            "slot": "56",
            "type": "t_array(t_uint256)45_storage",
            "contract": "ERC20Upgradeable",
            "src": "@openzeppelin/contracts-upgradeable/token/ERC20/ERC20Upgradeable.sol:400"
          },
          {
            "label": "SHAREHOLDER_STATUS",
            "offset": 0,
            "slot": "101",
            "type": "t_bytes32",
            "contract": "ShareholderRegistryBase",
            "src": "contracts/ShareholderRegistry/ShareholderRegistryBase.sol:9"
          },
          {
            "label": "INVESTOR_STATUS",
            "offset": 0,
            "slot": "102",
            "type": "t_bytes32",
            "contract": "ShareholderRegistryBase",
            "src": "contracts/ShareholderRegistry/ShareholderRegistryBase.sol:10"
          },
          {
            "label": "CONTRIBUTOR_STATUS",
            "offset": 0,
            "slot": "103",
            "type": "t_bytes32",
            "contract": "ShareholderRegistryBase",
            "src": "contracts/ShareholderRegistry/ShareholderRegistryBase.sol:11"
          },
          {
            "label": "MANAGING_BOARD_STATUS",
            "offset": 0,
            "slot": "104",
            "type": "t_bytes32",
            "contract": "ShareholderRegistryBase",
            "src": "contracts/ShareholderRegistry/ShareholderRegistryBase.sol:12"
          },
          {
            "label": "_voting",
            "offset": 0,
            "slot": "105",
            "type": "t_contract(IVoting)11408",
            "contract": "ShareholderRegistryBase",
            "src": "contracts/ShareholderRegistry/ShareholderRegistryBase.sol:14"
          },
          {
            "label": "_statuses",
            "offset": 0,
            "slot": "106",
            "type": "t_mapping(t_address,t_bytes32)",
            "contract": "ShareholderRegistryBase",
            "src": "contracts/ShareholderRegistry/ShareholderRegistryBase.sol:22"
          },
          {
            "label": "_currentSnapshotId",
            "offset": 0,
            "slot": "107",
            "type": "t_uint256",
            "contract": "Snapshottable",
            "src": "contracts/extensions/Snapshottable.sol:11"
          },
          {
            "label": "_totalSupplySnapshots",
            "offset": 0,
            "slot": "108",
            "type": "t_struct(TotalSupplySnapshots)10974_storage",
            "contract": "ShareholderRegistrySnapshot",
            "src": "contracts/ShareholderRegistry/ShareholderRegistrySnapshot.sol:16"
          },
          {
            "label": "_accountStatusAndBalanceSnapshots",
            "offset": 0,
            "slot": "110",
            "type": "t_mapping(t_address,t_struct(StatusAndBalanceSnapshots)10990_storage)",
            "contract": "ShareholderRegistrySnapshot",
            "src": "contracts/ShareholderRegistry/ShareholderRegistrySnapshot.sol:28"
          },
          {
            "label": "_roles",
            "offset": 0,
            "slot": "111",
            "type": "t_contract(DAORoles)12510",
            "contract": "HasRole",
            "src": "contracts/extensions/HasRole.sol:11"
          }
        ],
        "types": {
          "t_address": {
            "label": "address",
            "numberOfBytes": "20"
          },
          "t_array(t_struct(StatusAndBalance)10982_storage)dyn_storage": {
            "label": "struct ShareholderRegistrySnapshot.StatusAndBalance[]",
            "numberOfBytes": "32"
          },
          "t_array(t_uint256)45_storage": {
            "label": "uint256[45]",
            "numberOfBytes": "1440"
          },
          "t_array(t_uint256)50_storage": {
            "label": "uint256[50]",
            "numberOfBytes": "1600"
          },
          "t_array(t_uint256)dyn_storage": {
            "label": "uint256[]",
            "numberOfBytes": "32"
          },
          "t_bool": {
            "label": "bool",
            "numberOfBytes": "1"
          },
          "t_bytes32": {
            "label": "bytes32",
            "numberOfBytes": "32"
          },
          "t_contract(DAORoles)12510": {
            "label": "contract DAORoles",
            "numberOfBytes": "20"
          },
          "t_contract(IVoting)11408": {
            "label": "contract IVoting",
            "numberOfBytes": "20"
          },
          "t_mapping(t_address,t_bytes32)": {
            "label": "mapping(address => bytes32)",
            "numberOfBytes": "32"
          },
          "t_mapping(t_address,t_mapping(t_address,t_uint256))": {
            "label": "mapping(address => mapping(address => uint256))",
            "numberOfBytes": "32"
          },
          "t_mapping(t_address,t_struct(StatusAndBalanceSnapshots)10990_storage)": {
            "label": "mapping(address => struct ShareholderRegistrySnapshot.StatusAndBalanceSnapshots)",
            "numberOfBytes": "32"
          },
          "t_mapping(t_address,t_uint256)": {
            "label": "mapping(address => uint256)",
            "numberOfBytes": "32"
          },
          "t_string_storage": {
            "label": "string",
            "numberOfBytes": "32"
          },
          "t_struct(StatusAndBalance)10982_storage": {
            "label": "struct ShareholderRegistrySnapshot.StatusAndBalance",
            "members": [
              {
                "label": "status",
                "type": "t_bytes32",
                "offset": 0,
                "slot": "0"
              },
              {
                "label": "balance",
                "type": "t_uint256",
                "offset": 0,
                "slot": "1"
              }
            ],
            "numberOfBytes": "64"
          },
          "t_struct(StatusAndBalanceSnapshots)10990_storage": {
            "label": "struct ShareholderRegistrySnapshot.StatusAndBalanceSnapshots",
            "members": [
              {
                "label": "ids",
                "type": "t_array(t_uint256)dyn_storage",
                "offset": 0,
                "slot": "0"
              },
              {
                "label": "values",
                "type": "t_array(t_struct(StatusAndBalance)10982_storage)dyn_storage",
                "offset": 0,
                "slot": "1"
              }
            ],
            "numberOfBytes": "64"
          },
          "t_struct(TotalSupplySnapshots)10974_storage": {
            "label": "struct ShareholderRegistrySnapshot.TotalSupplySnapshots",
            "members": [
              {
                "label": "ids",
                "type": "t_array(t_uint256)dyn_storage",
                "offset": 0,
                "slot": "0"
              },
              {
                "label": "values",
                "type": "t_array(t_uint256)dyn_storage",
                "offset": 0,
                "slot": "1"
              }
            ],
            "numberOfBytes": "64"
          },
          "t_uint256": {
            "label": "uint256",
            "numberOfBytes": "32"
          },
          "t_uint8": {
            "label": "uint8",
            "numberOfBytes": "1"
          }
        }
      }
    },
    "a370d65b4fa790173a9d3b944e65ad164be8956dc9ecbdb5b474d156fd26ff0f": {
      "address": "0x9f6AcbA5e9f72aE9cbAa788b0ce8015fBd6aD291",
      "txHash": "0x0ba75203cb1ace9dc26a1356549ad853b00721ae9de4e5475d97f20a78b42c68",
      "layout": {
        "solcVersion": "0.8.16",
        "storage": [
          {
            "label": "_initialized",
            "offset": 0,
            "slot": "0",
            "type": "t_uint8",
            "contract": "Initializable",
            "src": "@openzeppelin/contracts-upgradeable/proxy/utils/Initializable.sol:62",
            "retypedFrom": "bool"
          },
          {
            "label": "_initializing",
            "offset": 1,
            "slot": "0",
            "type": "t_bool",
            "contract": "Initializable",
            "src": "@openzeppelin/contracts-upgradeable/proxy/utils/Initializable.sol:67"
          },
          {
            "label": "_currentResolutionId",
            "offset": 0,
            "slot": "1",
            "type": "t_uint256",
            "contract": "ResolutionManagerBase",
            "src": "contracts/ResolutionManager/ResolutionManagerBase.sol:72"
          },
          {
            "label": "_shareholderRegistry",
            "offset": 0,
            "slot": "2",
            "type": "t_contract(IShareholderRegistry)10361",
            "contract": "ResolutionManagerBase",
            "src": "contracts/ResolutionManager/ResolutionManagerBase.sol:74"
          },
          {
            "label": "_governanceToken",
            "offset": 0,
            "slot": "3",
            "type": "t_contract(IGovernanceToken)6652",
            "contract": "ResolutionManagerBase",
            "src": "contracts/ResolutionManager/ResolutionManagerBase.sol:75"
          },
          {
            "label": "_voting",
            "offset": 0,
            "slot": "4",
            "type": "t_contract(IVoting)11408",
            "contract": "ResolutionManagerBase",
            "src": "contracts/ResolutionManager/ResolutionManagerBase.sol:76"
          },
          {
            "label": "resolutionTypes",
            "offset": 0,
            "slot": "5",
            "type": "t_array(t_struct(ResolutionType)9054_storage)dyn_storage",
            "contract": "ResolutionManagerBase",
            "src": "contracts/ResolutionManager/ResolutionManagerBase.sol:78"
          },
          {
            "label": "resolutions",
            "offset": 0,
            "slot": "6",
            "type": "t_mapping(t_uint256,t_struct(Resolution)9091_storage)",
            "contract": "ResolutionManagerBase",
            "src": "contracts/ResolutionManager/ResolutionManagerBase.sol:80"
          },
          {
            "label": "__gap",
            "offset": 0,
            "slot": "7",
            "type": "t_array(t_uint256)50_storage",
            "contract": "ContextUpgradeable",
            "src": "@openzeppelin/contracts-upgradeable/utils/ContextUpgradeable.sol:36"
          },
          {
            "label": "_roles",
            "offset": 0,
            "slot": "57",
            "type": "t_contract(DAORoles)12510",
            "contract": "HasRole",
            "src": "contracts/extensions/HasRole.sol:11"
          }
        ],
        "types": {
          "t_address": {
            "label": "address",
            "numberOfBytes": "20"
          },
          "t_array(t_address)dyn_storage": {
            "label": "address[]",
            "numberOfBytes": "32"
          },
          "t_array(t_bytes_storage)dyn_storage": {
            "label": "bytes[]",
            "numberOfBytes": "32"
          },
          "t_array(t_struct(ResolutionType)9054_storage)dyn_storage": {
            "label": "struct ResolutionManagerBase.ResolutionType[]",
            "numberOfBytes": "32"
          },
          "t_array(t_uint256)50_storage": {
            "label": "uint256[50]",
            "numberOfBytes": "1600"
          },
          "t_bool": {
            "label": "bool",
            "numberOfBytes": "1"
          },
          "t_bytes_storage": {
            "label": "bytes",
            "numberOfBytes": "32"
          },
          "t_contract(DAORoles)12510": {
            "label": "contract DAORoles",
            "numberOfBytes": "20"
          },
          "t_contract(IGovernanceToken)6652": {
            "label": "contract IGovernanceToken",
            "numberOfBytes": "20"
          },
          "t_contract(IShareholderRegistry)10361": {
            "label": "contract IShareholderRegistry",
            "numberOfBytes": "20"
          },
          "t_contract(IVoting)11408": {
            "label": "contract IVoting",
            "numberOfBytes": "20"
          },
          "t_mapping(t_address,t_bool)": {
            "label": "mapping(address => bool)",
            "numberOfBytes": "32"
          },
          "t_mapping(t_address,t_uint256)": {
            "label": "mapping(address => uint256)",
            "numberOfBytes": "32"
          },
          "t_mapping(t_uint256,t_struct(Resolution)9091_storage)": {
            "label": "mapping(uint256 => struct ResolutionManagerBase.Resolution)",
            "numberOfBytes": "32"
          },
          "t_string_storage": {
            "label": "string",
            "numberOfBytes": "32"
          },
          "t_struct(Resolution)9091_storage": {
            "label": "struct ResolutionManagerBase.Resolution",
            "members": [
              {
                "label": "dataURI",
                "type": "t_string_storage",
                "offset": 0,
                "slot": "0"
              },
              {
                "label": "resolutionTypeId",
                "type": "t_uint256",
                "offset": 0,
                "slot": "1"
              },
              {
                "label": "approveTimestamp",
                "type": "t_uint256",
                "offset": 0,
                "slot": "2"
              },
              {
                "label": "snapshotId",
                "type": "t_uint256",
                "offset": 0,
                "slot": "3"
              },
              {
                "label": "yesVotesTotal",
                "type": "t_uint256",
                "offset": 0,
                "slot": "4"
              },
              {
                "label": "isNegative",
                "type": "t_bool",
                "offset": 0,
                "slot": "5"
              },
              {
                "label": "rejectionTimestamp",
                "type": "t_uint256",
                "offset": 0,
                "slot": "6"
              },
              {
                "label": "executionTo",
                "type": "t_array(t_address)dyn_storage",
                "offset": 0,
                "slot": "7"
              },
              {
                "label": "executionData",
                "type": "t_array(t_bytes_storage)dyn_storage",
                "offset": 0,
                "slot": "8"
              },
              {
                "label": "executionTimestamp",
                "type": "t_uint256",
                "offset": 0,
                "slot": "9"
              },
              {
                "label": "addressedContributor",
                "type": "t_address",
                "offset": 0,
                "slot": "10"
              },
              {
                "label": "hasVoted",
                "type": "t_mapping(t_address,t_bool)",
                "offset": 0,
                "slot": "11"
              },
              {
                "label": "hasVotedYes",
                "type": "t_mapping(t_address,t_bool)",
                "offset": 0,
                "slot": "12"
              },
              {
                "label": "lostVotingPower",
                "type": "t_mapping(t_address,t_uint256)",
                "offset": 0,
                "slot": "13"
              }
            ],
            "numberOfBytes": "448"
          },
          "t_struct(ResolutionType)9054_storage": {
            "label": "struct ResolutionManagerBase.ResolutionType",
            "members": [
              {
                "label": "name",
                "type": "t_string_storage",
                "offset": 0,
                "slot": "0"
              },
              {
                "label": "quorum",
                "type": "t_uint256",
                "offset": 0,
                "slot": "1"
              },
              {
                "label": "noticePeriod",
                "type": "t_uint256",
                "offset": 0,
                "slot": "2"
              },
              {
                "label": "votingPeriod",
                "type": "t_uint256",
                "offset": 0,
                "slot": "3"
              },
              {
                "label": "canBeNegative",
                "type": "t_bool",
                "offset": 0,
                "slot": "4"
              }
            ],
            "numberOfBytes": "160"
          },
          "t_uint256": {
            "label": "uint256",
            "numberOfBytes": "32"
          },
          "t_uint8": {
            "label": "uint8",
            "numberOfBytes": "1"
          }
        }
      }
    }
  }
}
